README.md
setup.py
FastAdminCLI/__init__.py
FastAdminCLI/cli.py
FastAdminCLI.egg-info/PKG-INFO
FastAdminCLI.egg-info/SOURCES.txt
FastAdminCLI.egg-info/dependency_links.txt
FastAdminCLI.egg-info/entry_points.txt
FastAdminCLI.egg-info/requires.txt
FastAdminCLI.egg-info/top_level.txt