Metadata-Version: 2.1
Name: FastAdminCLI
Version: 0.0.1
Summary: A colection of tools for working with FastAdmin project
Home-page: https://github.com/alphabotics/FastAdminCLI.git
Author: Quan Vu, Pycoders.vn
Author-email: info@quanvu.net, admin@pycoders.vn
License: UNKNOWN
Keywords: FastAdmin,Admin Dashboard
Platform: UNKNOWN
Classifier: Development Status :: 3 - Alpha
Classifier: Intended Audience :: Developers
Classifier: Topic :: Software Development :: Build Tools
Classifier: License :: OSI Approved :: MIT License
Classifier: Programming Language :: Python :: 3
Classifier: Programming Language :: Python :: 3.4
Classifier: Programming Language :: Python :: 3.5
Classifier: Programming Language :: Python :: 3.6
Classifier: Programming Language :: Python :: 3.7
Requires-Python: >=3.6
